halfling/__init__.py
halfling/_runner.py
halfling/compile.py
halfling/config.py
halfling/exceptions.py
halfling/main.py
halfling/shortcuts.py
halfling/tasks.py
halfling/utils.py
halfling-0.2.0.dist-info/LICENSE
halfling-0.2.0.dist-info/METADATA
halfling-0.2.0.dist-info/WHEEL
halfling-0.2.0.dist-info/entry_points.txt
halfling-0.2.0.dist-info/top_level.txt
halfling-0.2.0.dist-info/RECORD
