Metadata-Version: 2.1
Name: halfling
Version: 0.2.0
Summary: Small, practical build and task automation system written in Python.
Home-page: https://github.com/aloebs29/halfling
Author: Andrew Loebs
License: MIT
Platform: UNKNOWN
